odoo8_addon_crm_construction_architect-8.0.0.1.0-py2.7-nspkg.pth
odoo_addons/crm_construction_architect/views.xml
odoo_addons/crm_construction_architect/models.py
odoo_addons/crm_construction_architect/__openerp__.py
odoo_addons/crm_construction_architect/__init__.py
odoo_addons/crm_construction_architect/README.rst
odoo_addons/crm_construction_architect/oca_dependencies.txt
odoo_addons/crm_construction_architect/i18n/construction_architect_crm.pot
odoo_addons/crm_construction_architect/static/description/example-opportunity-treeview.png
odoo_addons/crm_construction_architect/static/description/index.html
odoo_addons/crm_construction_architect/static/description/example-opportunity-architect.png
odoo_addons/crm_construction_architect/static/description/icon.png
odoo8_addon_crm_construction_architect-8.0.0.1.0.dist-info/top_level.txt
odoo8_addon_crm_construction_architect-8.0.0.1.0.dist-info/WHEEL
odoo8_addon_crm_construction_architect-8.0.0.1.0.dist-info/RECORD
odoo8_addon_crm_construction_architect-8.0.0.1.0.dist-info/metadata.json
odoo8_addon_crm_construction_architect-8.0.0.1.0.dist-info/DESCRIPTION.rst
odoo8_addon_crm_construction_architect-8.0.0.1.0.dist-info/METADATA
odoo8_addon_crm_construction_architect-8.0.0.1.0.dist-info/namespace_packages.txt
